llama_index/indices/managed/colbert/__init__.py
llama_index/indices/managed/colbert/base.py
llama_index/indices/managed/colbert/retriever.py
llama_index_indices_managed_colbert-0.5.1.dist-info/METADATA
llama_index_indices_managed_colbert-0.5.1.dist-info/WHEEL
llama_index_indices_managed_colbert-0.5.1.dist-info/licenses/LICENSE
llama_index_indices_managed_colbert-0.5.1.dist-info/RECORD
