Metadata-Version: 2.4
Name: llama-index-indices-managed-colbert
Version: 0.5.1
Summary: llama-index managed colbert integration
Author-email: Your Name <you@example.com>
License-Expression: MIT
License-File: LICENSE
Requires-Python: <4.0,>=3.9
Requires-Dist: llama-index-core<0.15,>=0.13.0
